pymechtest/__init__.py
pymechtest/base.py
pymechtest/compression.py
pymechtest/flexure.py
pymechtest/py.typed
pymechtest/shear.py
pymechtest/tensile.py
pymechtest-0.1.4.dist-info/LICENSE
pymechtest-0.1.4.dist-info/METADATA
pymechtest-0.1.4.dist-info/WHEEL
pymechtest-0.1.4.dist-info/top_level.txt
pymechtest-0.1.4.dist-info/RECORD
