Metadata-Version: 2.1
Name: pymechtest
Version: 0.1.4
Summary: Python package to automate the boring bits of mechanical test data analysis!
Home-page: https://github.com/FollowTheProcess/pymechtest
Author: Tom Fleet
Author-email: tomfleet2018@gmail.com
License: GNU General Public License v3
Project-URL: Documentation, https://FollowTheProcess.github.io/pymechtest/
Platform: UNKNOWN
Classifier: Development Status :: 3 - Alpha
Classifier: Natural Language :: English
Classifier: Programming Language :: Python :: 3
Classifier: Programming Language :: Python :: 3.7
Classifier: Programming Language :: Python :: 3.8
Classifier: Programming Language :: Python :: 3.9
Classifier: Intended Audience :: Science/Research
Classifier: License :: OSI Approved :: GNU General Public License v3 (GPLv3)
Classifier: Operating System :: OS Independent
Classifier: Topic :: Scientific/Engineering
Classifier: Typing :: Typed
Requires-Python: >=3.7
Requires-Dist: pandas (>=1.1.4)
Requires-Dist: numpy (>=1.19.4)
Requires-Dist: altair (>=4.1.0)
Requires-Dist: altair-data-server (>=0.4.1)
Requires-Dist: altair-saver (>=0.5.0)
Provides-Extra: cov
Requires-Dist: coverage (>=5.3.1) ; extra == 'cov'
Requires-Dist: toml (>=0.10.2) ; extra == 'cov'
Provides-Extra: dev
Requires-Dist: bump2version (>=1.0.1) ; extra == 'dev'
Requires-Dist: flake8 (>=3.8.4) ; extra == 'dev'
Requires-Dist: isort (>=5.6.4) ; extra == 'dev'
Requires-Dist: nox (>=2020.8.22) ; extra == 'dev'
Requires-Dist: black (>=20.8b1) ; extra == 'dev'
Requires-Dist: twine (>=3.2.0) ; extra == 'dev'
Requires-Dist: pytest (>=6.1.2) ; extra == 'dev'
Requires-Dist: pytest-cov (>=2.10.1) ; extra == 'dev'
Requires-Dist: mypy (>=0.790) ; extra == 'dev'
Requires-Dist: mkdocs (>=1.1.2) ; extra == 'dev'
Requires-Dist: mkdocs-material (>=6.2.2) ; extra == 'dev'
Requires-Dist: mkdocstrings (>=0.13.6) ; extra == 'dev'
Requires-Dist: build (>=0.1.0) ; extra == 'dev'
Provides-Extra: docs
Requires-Dist: mkdocs (>=1.1.2) ; extra == 'docs'
Requires-Dist: mkdocs-material (>=6.2.2) ; extra == 'docs'
Requires-Dist: mkdocstrings (>=0.13.6) ; extra == 'docs'
Provides-Extra: lint
Requires-Dist: flake8 (>=3.8.4) ; extra == 'lint'
Requires-Dist: isort (>=5.6.4) ; extra == 'lint'
Requires-Dist: black (>=20.8b1) ; extra == 'lint'
Requires-Dist: mypy (>=0.790) ; extra == 'lint'
Provides-Extra: test
Requires-Dist: pytest (>=6.1.2) ; extra == 'test'
Requires-Dist: pytest-cov (>=2.10.1) ; extra == 'test'
